pypendency/__init__.py
pypendency/argument.py
pypendency/builder.py
pypendency/container.py
pypendency/definition.py
pypendency/exceptions.py
pypendency/on_container_resolved_callable.py
pypendency/tag.py
pypendency/loaders/__init__.py
pypendency/loaders/exceptions.py
pypendency/loaders/loader.py
pypendency/loaders/py_loader.py
pypendency/loaders/yaml_loader.py
pypendency/types/__init__.py
pypendency/types/python_loadable_module.py
pypendency-0.5.0.dist-info/LICENSE
pypendency-0.5.0.dist-info/METADATA
pypendency-0.5.0.dist-info/WHEEL
pypendency-0.5.0.dist-info/top_level.txt
pypendency-0.5.0.dist-info/RECORD
