Metadata-Version: 2.1
Name: pypendency
Version: 0.5.0
Summary: A dependency injection tool for python
Home-page: https://github.com/Feverup/pypendency
Author: Fever - Platform Squad
Author-email: platform@feverup.com
License: MIT License
Platform: UNKNOWN
Classifier: Intended Audience :: Developers
Classifier: License :: OSI Approved :: MIT License
Classifier: Operating System :: OS Independent
Classifier: Programming Language :: Python :: 3.7
Classifier: Programming Language :: Python :: 3.8
Classifier: Operating System :: OS Independent
Classifier: Topic :: Software Development :: Libraries
Classifier: Typing :: Typed
Requires-Python: >=3.7
Requires-Dist: pyyaml
